django_inlinecss/__init__.py
django_inlinecss/__version__.py
django_inlinecss/conf.py
django_inlinecss/css_loaders.py
django_inlinecss/engines.py
django_inlinecss/models.py
django_inlinecss/templatetags/__init__.py
django_inlinecss/templatetags/inlinecss.py
django_inlinecss/tests/__init__.py
django_inlinecss/tests/test_css_loaders.py
django_inlinecss/tests/test_templatetags.py
django_inlinecss/tests/static/bar.css
django_inlinecss/tests/static/foo.css
django_inlinecss/tests/static/foobar.css
django_inlinecss/tests/templates/base.html
django_inlinecss/tests/templates/comments_are_ignored.html
django_inlinecss/tests/templates/context_vars_render_first.html
django_inlinecss/tests/templates/inline_css.html
django_inlinecss/tests/templates/multiple_staticfiles_css.html
django_inlinecss/tests/templates/single_staticfiles_css.html
django_inlinecss/tests/templates/template_inheritance.html
django_inlinecss/tests/templates/template_inheritance_base.html
django_inlinecss/tests/templates/unicode_context_variables.html
django_inlinecss/tests/templates/variable_and_string_defined_staticfiles_css.html
django_inlinecss/tests/templates/variable_defined_staticfiles_css.html
django_inlinecss_redux-0.4.0.dist-info/LICENSE.md
django_inlinecss_redux-0.4.0.dist-info/METADATA
django_inlinecss_redux-0.4.0.dist-info/WHEEL
django_inlinecss_redux-0.4.0.dist-info/top_level.txt
django_inlinecss_redux-0.4.0.dist-info/RECORD
