Metadata-Version: 2.1
Name: django-inlinecss-redux
Version: 0.4.0
Summary: A Django app useful for inlining CSS (primarily for e-mails)
Home-page: https://github.com/WhyNotHugo/django-inlinecss
Author: Philip Kimmey
Author-email: philip@rover.com
License: MIT
Keywords: html,css,inline,style,email
Platform: UNKNOWN
Classifier: Environment :: Other Environment
Classifier: Environment :: Web Environment
Classifier: Intended Audience :: Developers
Classifier: License :: OSI Approved :: MIT License
Classifier: Operating System :: OS Independent
Classifier: Programming Language :: Python
Classifier: Programming Language :: Python :: 3
Classifier: Programming Language :: Python :: 3.6
Classifier: Programming Language :: Python :: 3.7
Classifier: Programming Language :: Python :: 3.8
Classifier: Programming Language :: Python :: 3.9
Classifier: Topic :: Communications :: Email
Classifier: Topic :: Text Processing :: Markup :: HTML
License-File: LICENSE.md
Requires-Dist: Django (>=2.2)
Requires-Dist: pynliner
Provides-Extra: flake8
Requires-Dist: flake8 (==3.8.0) ; extra == 'flake8'
Requires-Dist: flake8-isort (==2.6.0) ; extra == 'flake8'
Requires-Dist: isort (==4.3.4) ; extra == 'flake8'
Requires-Dist: testfixtures (==6.3.0) ; extra == 'flake8'
Provides-Extra: tests
Requires-Dist: mock (==2.0.0) ; extra == 'tests'
Requires-Dist: pytest (==4.3.1) ; extra == 'tests'
Requires-Dist: pytest-django (==3.4.8) ; extra == 'tests'
